pipeline_staging_properties_pkg/__init__.py
pipeline_staging_properties_pkg/pipeline_staging_properties.py
pkg_newfinalcustom_pipeline_staging_final-0.1.0.dist-info/LICENSE
pkg_newfinalcustom_pipeline_staging_final-0.1.0.dist-info/METADATA
pkg_newfinalcustom_pipeline_staging_final-0.1.0.dist-info/WHEEL
pkg_newfinalcustom_pipeline_staging_final-0.1.0.dist-info/top_level.txt
pkg_newfinalcustom_pipeline_staging_final-0.1.0.dist-info/RECORD
